infracrypt/__init__.py
infracrypt/__main__.py
infracrypt/pyfile_encode.py
infracrypt/pyfile_parser.py
infracrypt-1.0.dist-info/LICENSE
infracrypt-1.0.dist-info/METADATA
infracrypt-1.0.dist-info/WHEEL
infracrypt-1.0.dist-info/entry_points.txt
infracrypt-1.0.dist-info/top_level.txt
infracrypt-1.0.dist-info/RECORD
